[{
  "_id": "190120010406accde35c",
  "name": "test",
  "body": "<p>test 1</p>",
  "isDefault": false,
  "author": "1"
},{
  "_id": "1901200104120a8fcc04",
  "name": "Chữ ký 01",
  "body": "<p>------------------------------------------------</p><p><strong>DOCORP JSC</strong></p><p><strong>CÔNG TY CỔ PHẦN DOCORP</strong></p><p><strong>Address: Số 23 Trường Thi 1, Phường Hòa Thuận Tây, Quận Hải Châu, Thành phố Đà Nẵng</strong></p><p><strong>Phone : 0905.043.312 (Ms Thúy Phượng)</strong></p>",
  "isDefault": true,
  "author": "1"
}]